lsada/__init__.py
lsada/config/__init__.py
lsada/config/api_config.py
lsada/config/config_manager.py
lsada/evaluator/__init__.py
lsada/evaluator/base_evaluator.py
lsada/evaluator/evaluator.py
lsada/evaluator/prompt_generator.py
lsada/evaluator/registry.py
lsada/evaluator/task_manager.py
lsada/models/__init__.py
lsada/models/anthropic.py
lsada/models/cloudverse.py
lsada/models/llm_manager.py
lsada/models/openai.py
lsada/pool/__init__.py
lsada/pool/metrics_pool.json
lsada/pool/task_pool.json
lsada/utils/llm_parser.py
lsada/utils/metrics.py
lsada-1.9.0.dist-info/METADATA
lsada-1.9.0.dist-info/WHEEL
lsada-1.9.0.dist-info/top_level.txt
lsada-1.9.0.dist-info/RECORD
